[
    {
        "key": "8935",
        "code": "EEPS 0010",
        "title": "Face of the Earth",
        "crn": "26068",
        "no": "S01",
        "total": "1",
        "schd": "S",
        "stat": "A",
        "hide": "",
        "isCancelled": "",
        "meets": "MWF 1-1:50p",
        "mpkey": "2046",
        "meetingTimes": "[{\"meet_day\":\"0\",\"start_time\":\"1300\",\"end_time\":\"1350\"},{\"meet_day\":\"2\",\"start_time\":\"1300\",\"end_time\":\"1350\"},{\"meet_day\":\"4\",\"start_time\":\"1300\",\"end_time\":\"1350\"}]",
        "instr": "S. Parman",
        "start_date": "2022-01-26",
        "end_date": "2022-05-20",
        "permreq": "N",
        "rpt": "N",
        "open_enroll": "",
        "acad_career": "",
        "cart_opts": "{\"grade_mode\":{\"cart_field\":\"p_gmod\",\"enabled\":true,\"options\":[{\"value\":\"G\",\"label\":\"Standard ABC/No Credit\",\"default\":true,\"selected\":\"selected\"},{\"value\":\"A\",\"label\":\"Audit\",\"default\":false,\"selected\":\"\"},{\"value\":\"S\",\"label\":\"Satisfactory/No Credit\",\"default\":false,\"selected\":\"\"}]},\"credit_hrs\":{\"cartField\":\"p_hours\",\"enabled\":true,\"options\":[{\"value\":\"1\",\"label\":\"1\",\"default\":true,\"selected\":\"selected\"}]},\"swap_section_with\":{\"enabled\":true,\"options\":[{\"value\":\"\",\"label\":\"Not Applicable\",\"default\":true,\"selected\":\"selected\"}]}}",
        "linked_crns": "",
        "auto_enroll_sections": "",
        "is_enroll_section": "",
        "rfam": "2153",
        "lrfam": "",
        "changehash": "n85Juh2NLkJzr7q6r5pCcg",
        "srcdb": "202120"
    },
    {
        "key": "2501",
        "code": "EEPS 0050",
        "title": "Mars, Moon, and the Earth",
        "crn": "16884",
        "no": "S01",
        "total": "1",
        "schd": "S",
        "stat": "A",
        "hide": "",
        "isCancelled": "",
        "meets": "MWF 2-2:50p",
        "mpkey": "2053",
        "meetingTimes": "[{\"meet_day\":\"0\",\"start_time\":\"1400\",\"end_time\":\"1450\"},{\"meet_day\":\"2\",\"start_time\":\"1400\",\"end_time\":\"1450\"},{\"meet_day\":\"4\",\"start_time\":\"1400\",\"end_time\":\"1450\"}]",
        "instr": "J. Mustard",
        "start_date": "2021-09-08",
        "end_date": "2021-12-21",
        "permreq": "N",
        "rpt": "N",
        "open_enroll": "",
        "acad_career": "",
        "cart_opts": "{\"grade_mode\":{\"cart_field\":\"p_gmod\",\"enabled\":true,\"options\":[{\"value\":\"G\",\"label\":\"Standard ABC/No Credit\",\"default\":true,\"selected\":\"selected\"},{\"value\":\"A\",\"label\":\"Audit\",\"default\":false,\"selected\":\"\"},{\"value\":\"S\",\"label\":\"Satisfactory/No Credit\",\"default\":false,\"selected\":\"\"}]},\"credit_hrs\":{\"cartField\":\"p_hours\",\"enabled\":true,\"options\":[{\"value\":\"1\",\"label\":\"1\",\"default\":true,\"selected\":\"selected\"}]},\"swap_section_with\":{\"enabled\":true,\"options\":[{\"value\":\"\",\"label\":\"Not Applicable\",\"default\":true,\"selected\":\"selected\"}]}}",
        "linked_crns": "",
        "auto_enroll_sections": "",
        "is_enroll_section": "",
        "rfam": "2153",
        "lrfam": "",
        "changehash": "xfppwfejfbBnoMNCfB2Mgg",
        "srcdb": "202110"
    },
    {
        "key": "2502",
        "code": "EEPS 0070",
        "title": "Introduction to Oceanography",
        "crn": "16897",
        "no": "S01",
        "total": "1",
        "schd": "S",
        "stat": "A",
        "hide": "",
        "isCancelled": "",
        "meets": "MWF 1-1:50p",
        "mpkey": "2046",
        "meetingTimes": "[{\"meet_day\":\"0\",\"start_time\":\"1300\",\"end_time\":\"1350\"},{\"meet_day\":\"2\",\"start_time\":\"1300\",\"end_time\":\"1350\"},{\"meet_day\":\"4\",\"start_time\":\"1300\",\"end_time\":\"1350\"}]",
        "instr": "S. Clemens",
        "start_date": "2021-09-08",
        "end_date": "2021-12-21",
        "permreq": "N",
        "rpt": "N",
        "open_enroll": "",
        "acad_career": "",
        "cart_opts": "{\"grade_mode\":{\"cart_field\":\"p_gmod\",\"enabled\":true,\"options\":[{\"value\":\"G\",\"label\":\"Standard ABC/No Credit\",\"default\":true,\"selected\":\"selected\"},{\"value\":\"A\",\"label\":\"Audit\",\"default\":false,\"selected\":\"\"},{\"value\":\"S\",\"label\":\"Satisfactory/No Credit\",\"default\":false,\"selected\":\"\"}]},\"credit_hrs\":{\"cartField\":\"p_hours\",\"enabled\":true,\"options\":[{\"value\":\"1\",\"label\":\"1\",\"default\":true,\"selected\":\"selected\"}]},\"swap_section_with\":{\"enabled\":true,\"options\":[{\"value\":\"\",\"label\":\"Not Applicable\",\"default\":true,\"selected\":\"selected\"}]}}",
        "linked_crns": "",
        "auto_enroll_sections": "",
        "is_enroll_section": "",
        "rfam": "2153",
        "lrfam": "",
        "changehash": "d54E8A32+t3f58qPE7FM0Q",
        "srcdb": "202110"
    },
    {
        "key": "2503",
        "code": "EEPS 0160I",
        "title": "Diamonds",
        "crn": "16882",
        "no": "S01",
        "total": "1",
        "schd": "S",
        "stat": "A",
        "hide": "",
        "isCancelled": "",
        "meets": "TTh 2:30-3:50p",
        "mpkey": "2035",
        "meetingTimes": "[{\"meet_day\":\"1\",\"start_time\":\"1430\",\"end_time\":\"1550\"},{\"meet_day\":\"3\",\"start_time\":\"1430\",\"end_time\":\"1550\"}]",
        "instr": "S. Parman",
        "start_date": "2021-09-08",
        "end_date": "2021-12-21",
        "permreq": "Y",
        "rpt": "N",
        "open_enroll": "",
        "acad_career": "",
        "cart_opts": "{\"grade_mode\":{\"cart_field\":\"p_gmod\",\"enabled\":true,\"options\":[{\"value\":\"G\",\"label\":\"Standard ABC/No Credit\",\"default\":true,\"selected\":\"selected\"},{\"value\":\"A\",\"label\":\"Audit\",\"default\":false,\"selected\":\"\"},{\"value\":\"S\",\"label\":\"Satisfactory/No Credit\",\"default\":false,\"selected\":\"\"}]},\"credit_hrs\":{\"cartField\":\"p_hours\",\"enabled\":true,\"options\":[{\"value\":\"1\",\"label\":\"1\",\"default\":true,\"selected\":\"selected\"}]},\"swap_section_with\":{\"enabled\":true,\"options\":[{\"value\":\"\",\"label\":\"Not Applicable\",\"default\":true,\"selected\":\"selected\"}]}}",
        "linked_crns": "",
        "auto_enroll_sections": "",
        "is_enroll_section": "",
        "rfam": "2164",
        "lrfam": "",
        "changehash": "Qj4SwpACiX8MUfU9myT2jg",
        "srcdb": "202110"
    },
    {
        "key": "2504",
        "code": "EEPS 0160P",
        "title": "From Human Migration to Solving Crimes: The World of Forensic Isotopes",
        "crn": "18038",
        "no": "S01",
        "total": "1",
        "schd": "S",
        "stat": "A",
        "hide": "",
        "isCancelled": "",
        "meets": "TTh 10:30-11:50a",
        "mpkey": "2026",
        "meetingTimes": "[{\"meet_day\":\"1\",\"start_time\":\"1030\",\"end_time\":\"1150\"},{\"meet_day\":\"3\",\"start_time\":\"1030\",\"end_time\":\"1150\"}]",
        "instr": "A. Saal",
        "start_date": "2021-09-08",
        "end_date": "2021-12-21",
        "permreq": "N",
        "rpt": "N",
        "open_enroll": "",
        "acad_career": "",
        "cart_opts": "{\"grade_mode\":{\"cart_field\":\"p_gmod\",\"enabled\":true,\"options\":[{\"value\":\"G\",\"label\":\"Standard ABC/No Credit\",\"default\":true,\"selected\":\"selected\"},{\"value\":\"A\",\"label\":\"Audit\",\"default\":false,\"selected\":\"\"},{\"value\":\"S\",\"label\":\"Satisfactory/No Credit\",\"default\":false,\"selected\":\"\"}]},\"credit_hrs\":{\"cartField\":\"p_hours\",\"enabled\":true,\"options\":[{\"value\":\"1\",\"label\":\"1\",\"default\":true,\"selected\":\"selected\"}]},\"swap_section_with\":{\"enabled\":true,\"options\":[{\"value\":\"\",\"label\":\"Not Applicable\",\"default\":true,\"selected\":\"selected\"}]}}",
        "linked_crns": "",
        "auto_enroll_sections": "",
        "is_enroll_section": "",
        "rfam": "2153",
        "lrfam": "",
        "changehash": "LMt05ldkMg8DYxOD+P4taQ",
        "srcdb": "202110"
    },
    {
        "key": "2505",
        "code": "EEPS 0220",
        "title": "Earth Processes",
        "crn": "16886",
        "no": "S01",
        "total": "3",
        "schd": "S",
        "stat": "A",
        "hide": "",
        "isCancelled": "",
        "meets": "TTh 10:30-11:50a",
        "mpkey": "2026",
        "meetingTimes": "[{\"meet_day\":\"1\",\"start_time\":\"1030\",\"end_time\":\"1150\"},{\"meet_day\":\"3\",\"start_time\":\"1030\",\"end_time\":\"1150\"}]",
        "instr": "Fischer/Hirth",
        "start_date": "2021-09-08",
        "end_date": "2021-12-21",
        "permreq": "N",
        "rpt": "N",
        "open_enroll": "",
        "acad_career": "",
        "cart_opts": "{\"grade_mode\":{\"cart_field\":\"p_gmod\",\"enabled\":true,\"options\":[{\"value\":\"G\",\"label\":\"Standard ABC/No Credit\",\"default\":true,\"selected\":\"selected\"},{\"value\":\"A\",\"label\":\"Audit\",\"default\":false,\"selected\":\"\"},{\"value\":\"S\",\"label\":\"Satisfactory/No Credit\",\"default\":false,\"selected\":\"\"}]},\"credit_hrs\":{\"cartField\":\"p_hours\",\"enabled\":true,\"options\":[{\"value\":\"1\",\"label\":\"1\",\"default\":true,\"selected\":\"selected\"}]},\"swap_section_with\":{\"enabled\":true,\"options\":[{\"value\":\"\",\"label\":\"Not Applicable\",\"default\":true,\"selected\":\"selected\"}]}}",
        "linked_crns": "",
        "auto_enroll_sections": "",
        "is_enroll_section": "",
        "rfam": "2151",
        "lrfam": "",
        "changehash": "zjc2nqPlAzZCY+YpSZX0EA",
        "srcdb": "202110"
    },
    {
        "key": "8936",
        "code": "EEPS 0230",
        "title": "Geochemistry: Earth and Planetary Materials and Processes",
        "crn": "26069",
        "no": "S01",
        "total": "1",
        "schd": "S",
        "stat": "A",
        "hide": "",
        "isCancelled": "",
        "meets": "TTh 1-2:20p",
        "mpkey": "2020",
        "meetingTimes": "[{\"meet_day\":\"1\",\"start_time\":\"1300\",\"end_time\":\"1420\"},{\"meet_day\":\"3\",\"start_time\":\"1300\",\"end_time\":\"1420\"}]",
        "instr": "A. Saal",
        "start_date": "2022-01-26",
        "end_date": "2022-05-20",
        "permreq": "N",
        "rpt": "N",
        "open_enroll": "",
        "acad_career": "",
        "cart_opts": "{\"grade_mode\":{\"cart_field\":\"p_gmod\",\"enabled\":true,\"options\":[{\"value\":\"G\",\"label\":\"Standard ABC/No Credit\",\"default\":true,\"selected\":\"selected\"},{\"value\":\"A\",\"label\":\"Audit\",\"default\":false,\"selected\":\"\"},{\"value\":\"S\",\"label\":\"Satisfactory/No Credit\",\"default\":false,\"selected\":\"\"}]},\"credit_hrs\":{\"cartField\":\"p_hours\",\"enabled\":true,\"options\":[{\"value\":\"1\",\"label\":\"1\",\"default\":true,\"selected\":\"selected\"}]},\"swap_section_with\":{\"enabled\":true,\"options\":[{\"value\":\"\",\"label\":\"Not Applicable\",\"default\":true,\"selected\":\"selected\"}]}}",
        "linked_crns": "",
        "auto_enroll_sections": "",
        "is_enroll_section": "",
        "rfam": "2151",
        "lrfam": "",
        "changehash": "/FrUblvUhY091eiOjgnaxA",
        "srcdb": "202120"
    },
    {
        "key": "8937",
        "code": "EEPS 0240",
        "title": "Earth: Evolution of a Habitable Planet",
        "crn": "26075",
        "no": "S01",
        "total": "1",
        "schd": "S",
        "stat": "A",
        "hide": "",
        "isCancelled": "",
        "meets": "MWF 11-11:50a",
        "mpkey": "2044",
        "meetingTimes": "[{\"meet_day\":\"0\",\"start_time\":\"1100\",\"end_time\":\"1150\"},{\"meet_day\":\"2\",\"start_time\":\"1100\",\"end_time\":\"1150\"},{\"meet_day\":\"4\",\"start_time\":\"1100\",\"end_time\":\"1150\"}]",
        "instr": "T. Herbert",
        "start_date": "2022-01-26",
        "end_date": "2022-05-20",
        "permreq": "N",
        "rpt": "N",
        "open_enroll": "",
        "acad_career": "",
        "cart_opts": "{\"grade_mode\":{\"cart_field\":\"p_gmod\",\"enabled\":true,\"options\":[{\"value\":\"G\",\"label\":\"Standard ABC/No Credit\",\"default\":true,\"selected\":\"selected\"},{\"value\":\"A\",\"label\":\"Audit\",\"default\":false,\"selected\":\"\"},{\"value\":\"S\",\"label\":\"Satisfactory/No Credit\",\"default\":false,\"selected\":\"\"}]},\"credit_hrs\":{\"cartField\":\"p_hours\",\"enabled\":true,\"options\":[{\"value\":\"1\",\"label\":\"1\",\"default\":true,\"selected\":\"selected\"}]},\"swap_section_with\":{\"enabled\":true,\"options\":[{\"value\":\"\",\"label\":\"Not Applicable\",\"default\":true,\"selected\":\"selected\"}]}}",
        "linked_crns": "",
        "auto_enroll_sections": "",
        "is_enroll_section": "",
        "rfam": "2151",
        "lrfam": "",
        "changehash": "LOWKyGTYGfetKvrhuSTmvQ",
        "srcdb": "202120"
    },
    {
        "key": "2508",
        "code": "EEPS 0350",
        "title": "Mathematical Methods of Fluid",
        "crn": "17678",
        "no": "S01",
        "total": "4",
        "schd": "S",
        "stat": "A",
        "hide": "",
        "isCancelled": "",
        "meets": "MWF 10-10:50a",
        "mpkey": "2041",
        "meetingTimes": "[{\"meet_day\":\"0\",\"start_time\":\"1000\",\"end_time\":\"1050\"},{\"meet_day\":\"2\",\"start_time\":\"1000\",\"end_time\":\"1050\"},{\"meet_day\":\"4\",\"start_time\":\"1000\",\"end_time\":\"1050\"}]",
        "instr": "B. Fox-Kemper",
        "start_date": "2021-09-08",
        "end_date": "2021-12-21",
        "permreq": "N",
        "rpt": "N",
        "open_enroll": "",
        "acad_career": "",
        "cart_opts": "{\"grade_mode\":{\"cart_field\":\"p_gmod\",\"enabled\":true,\"options\":[{\"value\":\"G\",\"label\":\"Standard ABC/No Credit\",\"default\":true,\"selected\":\"selected\"},{\"value\":\"A\",\"label\":\"Audit\",\"default\":false,\"selected\":\"\"},{\"value\":\"S\",\"label\":\"Satisfactory/No Credit\",\"default\":false,\"selected\":\"\"}]},\"credit_hrs\":{\"cartField\":\"p_hours\",\"enabled\":true,\"options\":[{\"value\":\"1\",\"label\":\"1\",\"default\":true,\"selected\":\"selected\"}]},\"swap_section_with\":{\"enabled\":true,\"options\":[{\"value\":\"\",\"label\":\"Not Applicable\",\"default\":true,\"selected\":\"selected\"}]}}",
        "linked_crns": "",
        "auto_enroll_sections": "",
        "is_enroll_section": "",
        "rfam": "2300",
        "lrfam": "",
        "changehash": "cIzl2xjrkxE9jRM3cogTFQ",
        "srcdb": "202110"
    },
    {
        "key": "8938",
        "code": "EEPS 0810",
        "title": "Planetary Geology",
        "crn": "26063",
        "no": "S01",
        "total": "1",
        "schd": "S",
        "stat": "A",
        "hide": "",
        "isCancelled": "",
        "meets": "MWF 10-10:50a",
        "mpkey": "2041",
        "meetingTimes": "[{\"meet_day\":\"0\",\"start_time\":\"1000\",\"end_time\":\"1050\"},{\"meet_day\":\"2\",\"start_time\":\"1000\",\"end_time\":\"1050\"},{\"meet_day\":\"4\",\"start_time\":\"1000\",\"end_time\":\"1050\"}]",
        "instr": "R. Milliken",
        "start_date": "2022-01-26",
        "end_date": "2022-05-20",
        "permreq": "N",
        "rpt": "N",
        "open_enroll": "",
        "acad_career": "",
        "cart_opts": "{\"grade_mode\":{\"cart_field\":\"p_gmod\",\"enabled\":true,\"options\":[{\"value\":\"G\",\"label\":\"Standard ABC/No Credit\",\"default\":true,\"selected\":\"selected\"},{\"value\":\"A\",\"label\":\"Audit\",\"default\":false,\"selected\":\"\"},{\"value\":\"S\",\"label\":\"Satisfactory/No Credit\",\"default\":false,\"selected\":\"\"}]},\"credit_hrs\":{\"cartField\":\"p_hours\",\"enabled\":true,\"options\":[{\"value\":\"1\",\"label\":\"1\",\"default\":true,\"selected\":\"selected\"}]},\"swap_section_with\":{\"enabled\":true,\"options\":[{\"value\":\"\",\"label\":\"Not Applicable\",\"default\":true,\"selected\":\"selected\"}]}}",
        "linked_crns": "",
        "auto_enroll_sections": "",
        "is_enroll_section": "",
        "rfam": "2153",
        "lrfam": "",
        "changehash": "1gODJl10F6tD/GrEKVJD9w",
        "srcdb": "202120"
    },
    {
        "key": "2512",
        "code": "EEPS 0830",
        "title": "Water in Our World",
        "crn": "18180",
        "no": "S01",
        "total": "1",
        "schd": "S",
        "stat": "A",
        "hide": "",
        "isCancelled": "",
        "meets": "F 12:30-3p",
        "mpkey": "3266",
        "meetingTimes": "[{\"meet_day\":\"4\",\"start_time\":\"1230\",\"end_time\":\"1500\"}]",
        "instr": "L. Smith",
        "start_date": "2021-09-08",
        "end_date": "2021-12-21",
        "permreq": "N",
        "rpt": "N",
        "open_enroll": "",
        "acad_career": "",
        "cart_opts": "{\"grade_mode\":{\"cart_field\":\"p_gmod\",\"enabled\":true,\"options\":[{\"value\":\"G\",\"label\":\"Standard ABC/No Credit\",\"default\":true,\"selected\":\"selected\"},{\"value\":\"A\",\"label\":\"Audit\",\"default\":false,\"selected\":\"\"},{\"value\":\"S\",\"label\":\"Satisfactory/No Credit\",\"default\":false,\"selected\":\"\"}]},\"credit_hrs\":{\"cartField\":\"p_hours\",\"enabled\":true,\"options\":[{\"value\":\"1\",\"label\":\"1\",\"default\":true,\"selected\":\"selected\"}]},\"swap_section_with\":{\"enabled\":true,\"options\":[{\"value\":\"\",\"label\":\"Not Applicable\",\"default\":true,\"selected\":\"selected\"}]}}",
        "linked_crns": "",
        "auto_enroll_sections": "",
        "is_enroll_section": "",
        "rfam": "2153",
        "lrfam": "",
        "changehash": "0CdzJPkk9UEhHBcf2mvAYA",
        "srcdb": "202110"
    },
    {
        "key": "8939",
        "code": "EEPS 0850",
        "title": "Weather and Climate",
        "crn": "26394",
        "no": "S01",
        "total": "1",
        "schd": "S",
        "stat": "A",
        "hide": "",
        "isCancelled": "",
        "meets": "TTh 10:30-11:50a",
        "mpkey": "2026",
        "meetingTimes": "[{\"meet_day\":\"1\",\"start_time\":\"1030\",\"end_time\":\"1150\"},{\"meet_day\":\"3\",\"start_time\":\"1030\",\"end_time\":\"1150\"}]",
        "instr": "M. Hastings",
        "start_date": "2022-01-26",
        "end_date": "2022-05-20",
        "permreq": "N",
        "rpt": "N",
        "open_enroll": "",
        "acad_career": "",
        "cart_opts": "{\"grade_mode\":{\"cart_field\":\"p_gmod\",\"enabled\":true,\"options\":[{\"value\":\"G\",\"label\":\"Standard ABC/No Credit\",\"default\":true,\"selected\":\"selected\"},{\"value\":\"A\",\"label\":\"Audit\",\"default\":false,\"selected\":\"\"},{\"value\":\"S\",\"label\":\"Satisfactory/No Credit\",\"default\":false,\"selected\":\"\"}]},\"credit_hrs\":{\"cartField\":\"p_hours\",\"enabled\":true,\"options\":[{\"value\":\"1\",\"label\":\"1\",\"default\":true,\"selected\":\"selected\"}]},\"swap_section_with\":{\"enabled\":true,\"options\":[{\"value\":\"\",\"label\":\"Not Applicable\",\"default\":true,\"selected\":\"selected\"}]}}",
        "linked_crns": "",
        "auto_enroll_sections": "",
        "is_enroll_section": "",
        "rfam": "2153",
        "lrfam": "",
        "changehash": "Phjksp95H90BkUN0x7j+fQ",
        "srcdb": "202120"
    },
    {
        "key": "8940",
        "code": "EEPS 1110",
        "title": "Descriptive Coastal and Estuarine Oceanography",
        "crn": "27384",
        "no": "S01",
        "total": "1",
        "schd": "S",
        "stat": "A",
        "hide": "",
        "isCancelled": "",
        "meets": "MWF 1-1:50p",
        "mpkey": "2046",
        "meetingTimes": "[{\"meet_day\":\"0\",\"start_time\":\"1300\",\"end_time\":\"1350\"},{\"meet_day\":\"2\",\"start_time\":\"1300\",\"end_time\":\"1350\"},{\"meet_day\":\"4\",\"start_time\":\"1300\",\"end_time\":\"1350\"}]",
        "instr": "S. Clemens",
        "start_date": "2022-01-26",
        "end_date": "2022-05-20",
        "permreq": "N",
        "rpt": "N",
        "open_enroll": "",
        "acad_career": "",
        "cart_opts": "{\"grade_mode\":{\"cart_field\":\"p_gmod\",\"enabled\":true,\"options\":[{\"value\":\"G\",\"label\":\"Standard ABC/No Credit\",\"default\":true,\"selected\":\"selected\"},{\"value\":\"A\",\"label\":\"Audit\",\"default\":false,\"selected\":\"\"},{\"value\":\"S\",\"label\":\"Satisfactory/No Credit\",\"default\":false,\"selected\":\"\"}]},\"credit_hrs\":{\"cartField\":\"p_hours\",\"enabled\":true,\"options\":[{\"value\":\"1\",\"label\":\"1\",\"default\":true,\"selected\":\"selected\"}]},\"swap_section_with\":{\"enabled\":true,\"options\":[{\"value\":\"\",\"label\":\"Not Applicable\",\"default\":true,\"selected\":\"selected\"}]}}",
        "linked_crns": "",
        "auto_enroll_sections": "",
        "is_enroll_section": "",
        "rfam": "2830",
        "lrfam": "",
        "changehash": "KvXJ0PAFokBtXfTh15XDJA",
        "srcdb": "202120"
    },
    {
        "key": "2513",
        "code": "EEPS 1120",
        "title": "Paleoceanography",
        "crn": "16894",
        "no": "S01",
        "total": "1",
        "schd": "S",
        "stat": "F",
        "hide": "",
        "isCancelled": "",
        "meets": "TTh 2:30-3:50p",
        "mpkey": "2035",
        "meetingTimes": "[{\"meet_day\":\"1\",\"start_time\":\"1430\",\"end_time\":\"1550\"},{\"meet_day\":\"3\",\"start_time\":\"1430\",\"end_time\":\"1550\"}]",
        "instr": "T. Herbert",
        "start_date": "2021-09-08",
        "end_date": "2021-12-21",
        "permreq": "N",
        "rpt": "N",
        "open_enroll": "",
        "acad_career": "",
        "cart_opts": "{\"grade_mode\":{\"cart_field\":\"p_gmod\",\"enabled\":true,\"options\":[{\"value\":\"G\",\"label\":\"Standard ABC/No Credit\",\"default\":true,\"selected\":\"selected\"},{\"value\":\"A\",\"label\":\"Audit\",\"default\":false,\"selected\":\"\"},{\"value\":\"S\",\"label\":\"Satisfactory/No Credit\",\"default\":false,\"selected\":\"\"}]},\"credit_hrs\":{\"cartField\":\"p_hours\",\"enabled\":true,\"options\":[{\"value\":\"1\",\"label\":\"1\",\"default\":true,\"selected\":\"selected\"}]},\"swap_section_with\":{\"enabled\":true,\"options\":[{\"value\":\"\",\"label\":\"Not Applicable\",\"default\":true,\"selected\":\"selected\"}]}}",
        "linked_crns": "",
        "auto_enroll_sections": "",
        "is_enroll_section": "",
        "rfam": "2154",
        "lrfam": "",
        "changehash": "3yK2rcox8OLtiCrRJWlr7A",
        "srcdb": "202110"
    },
    {
        "key": "2514",
        "code": "EEPS 1240",
        "title": "Stratigraphy and Sedimentation",
        "crn": "16892",
        "no": "S01",
        "total": "1",
        "schd": "S",
        "stat": "A",
        "hide": "",
        "isCancelled": "",
        "meets": "TTh 10:30-11:50a",
        "mpkey": "2026",
        "meetingTimes": "[{\"meet_day\":\"1\",\"start_time\":\"1030\",\"end_time\":\"1150\"},{\"meet_day\":\"3\",\"start_time\":\"1030\",\"end_time\":\"1150\"}]",
        "instr": "J. Russell",
        "start_date": "2021-09-08",
        "end_date": "2021-12-21",
        "permreq": "N",
        "rpt": "N",
        "open_enroll": "",
        "acad_career": "",
        "cart_opts": "{\"grade_mode\":{\"cart_field\":\"p_gmod\",\"enabled\":true,\"options\":[{\"value\":\"G\",\"label\":\"Standard ABC/No Credit\",\"default\":true,\"selected\":\"selected\"},{\"value\":\"A\",\"label\":\"Audit\",\"default\":false,\"selected\":\"\"},{\"value\":\"S\",\"label\":\"Satisfactory/No Credit\",\"default\":false,\"selected\":\"\"}]},\"credit_hrs\":{\"cartField\":\"p_hours\",\"enabled\":true,\"options\":[{\"value\":\"1\",\"label\":\"1\",\"default\":true,\"selected\":\"selected\"}]},\"swap_section_with\":{\"enabled\":true,\"options\":[{\"value\":\"\",\"label\":\"Not Applicable\",\"default\":true,\"selected\":\"selected\"}]}}",
        "linked_crns": "",
        "auto_enroll_sections": "",
        "is_enroll_section": "",
        "rfam": "2301",
        "lrfam": "",
        "changehash": "9CPV+V6kHGWQnJFv/GCw5A",
        "srcdb": "202110"
    },
    {
        "key": "8941",
        "code": "EEPS 1320",
        "title": "Introduction to Geographic Information Systems for Environmental Applications",
        "crn": "27648",
        "no": "S01",
        "total": "4",
        "schd": "S",
        "stat": "F",
        "hide": "",
        "isCancelled": "",
        "meets": "F 3-4:30p",
        "mpkey": "3323",
        "meetingTimes": "[{\"meet_day\":\"4\",\"start_time\":\"1500\",\"end_time\":\"1630\"}]",
        "instr": "K. Willis",
        "start_date": "2022-01-26",
        "end_date": "2022-05-20",
        "permreq": "N",
        "rpt": "N",
        "open_enroll": "",
        "acad_career": "",
        "cart_opts": "{\"grade_mode\":{\"cart_field\":\"p_gmod\",\"enabled\":true,\"options\":[{\"value\":\"S\",\"label\":\"Satisfactory/No Credit\",\"default\":true,\"selected\":\"selected\"},{\"value\":\"A\",\"label\":\"Audit\",\"default\":false,\"selected\":\"\"}]},\"credit_hrs\":{\"cartField\":\"p_hours\",\"enabled\":true,\"options\":[{\"value\":\"1\",\"label\":\"1\",\"default\":true,\"selected\":\"selected\"}]},\"swap_section_with\":{\"enabled\":true,\"options\":[{\"value\":\"\",\"label\":\"Not Applicable\",\"default\":true,\"selected\":\"selected\"}]}}",
        "linked_crns": "",
        "auto_enroll_sections": "",
        "is_enroll_section": "",
        "rfam": "2154",
        "lrfam": "",
        "changehash": "3W3Ch9x9N4+5ZEOqDrRYPw",
        "srcdb": "202120"
    },
    {
        "key": "8942",
        "code": "EEPS 1320",
        "title": "Introduction to Geographic Information Systems for Environmental Applications",
        "crn": "27649",
        "no": "L01",
        "total": "4",
        "schd": "L",
        "stat": "F",
        "hide": "",
        "isCancelled": "",
        "meets": "T 10:30-11:50a",
        "mpkey": "2117",
        "meetingTimes": "[{\"meet_day\":\"1\",\"start_time\":\"1030\",\"end_time\":\"1150\"}]",
        "instr": "K. Willis",
        "start_date": "2022-01-26",
        "end_date": "2022-05-20",
        "permreq": "N",
        "rpt": "N",
        "open_enroll": "",
        "acad_career": "",
        "cart_opts": "{\"grade_mode\":{\"cart_field\":\"p_gmod\",\"enabled\":false,\"options\":[{\"value\":\"\",\"label\":\"Not graded\",\"selected\":\"selected\",\"default\":true}]},\"credit_hrs\":{\"cartField\":\"p_hours\",\"enabled\":true,\"options\":[{\"value\":\"0\",\"label\":\"0\",\"default\":true,\"selected\":\"selected\"}]},\"swap_section_with\":{\"enabled\":true,\"options\":[{\"value\":\"\",\"label\":\"Not Applicable\",\"default\":true,\"selected\":\"selected\"}]}}",
        "linked_crns": "",
        "auto_enroll_sections": "",
        "is_enroll_section": "",
        "rfam": "2154",
        "lrfam": "",
        "changehash": "NgSqOX4GXF7IYl82ApBf8g",
        "srcdb": "202120"
    },
    {
        "key": "8943",
        "code": "EEPS 1320",
        "title": "Introduction to Geographic Information Systems for Environmental Applications",
        "crn": "27650",
        "no": "L02",
        "total": "4",
        "schd": "L",
        "stat": "F",
        "hide": "",
        "isCancelled": "",
        "meets": "T 1-2:20p",
        "mpkey": "2118",
        "meetingTimes": "[{\"meet_day\":\"1\",\"start_time\":\"1300\",\"end_time\":\"1420\"}]",
        "instr": "K. Willis",
        "start_date": "2022-01-26",
        "end_date": "2022-05-20",
        "permreq": "N",
        "rpt": "N",
        "open_enroll": "",
        "acad_career": "",
        "cart_opts": "{\"grade_mode\":{\"cart_field\":\"p_gmod\",\"enabled\":false,\"options\":[{\"value\":\"\",\"label\":\"Not graded\",\"selected\":\"selected\",\"default\":true}]},\"credit_hrs\":{\"cartField\":\"p_hours\",\"enabled\":true,\"options\":[{\"value\":\"0\",\"label\":\"0\",\"default\":true,\"selected\":\"selected\"}]},\"swap_section_with\":{\"enabled\":true,\"options\":[{\"value\":\"\",\"label\":\"Not Applicable\",\"default\":true,\"selected\":\"selected\"}]}}",
        "linked_crns": "",
        "auto_enroll_sections": "",
        "is_enroll_section": "",
        "rfam": "2154",
        "lrfam": "",
        "changehash": "V5zeqhhZiNXc8sg0qanYkw",
        "srcdb": "202120"
    },
    {
        "key": "8944",
        "code": "EEPS 1320",
        "title": "Introduction to Geographic Information Systems for Environmental Applications",
        "crn": "27651",
        "no": "L03",
        "total": "4",
        "schd": "L",
        "stat": "F",
        "hide": "",
        "isCancelled": "",
        "meets": "Th 10:30-11:50a",
        "mpkey": "2048",
        "meetingTimes": "[{\"meet_day\":\"3\",\"start_time\":\"1030\",\"end_time\":\"1150\"}]",
        "instr": "K. Willis",
        "start_date": "2022-01-26",
        "end_date": "2022-05-20",
        "permreq": "N",
        "rpt": "N",
        "open_enroll": "",
        "acad_career": "",
        "cart_opts": "{\"grade_mode\":{\"cart_field\":\"p_gmod\",\"enabled\":false,\"options\":[{\"value\":\"\",\"label\":\"Not graded\",\"selected\":\"selected\",\"default\":true}]},\"credit_hrs\":{\"cartField\":\"p_hours\",\"enabled\":true,\"options\":[{\"value\":\"0\",\"label\":\"0\",\"default\":true,\"selected\":\"selected\"}]},\"swap_section_with\":{\"enabled\":true,\"options\":[{\"value\":\"\",\"label\":\"Not Applicable\",\"default\":true,\"selected\":\"selected\"}]}}",
        "linked_crns": "",
        "auto_enroll_sections": "",
        "is_enroll_section": "",
        "rfam": "2154",
        "lrfam": "",
        "changehash": "qOA2k6sEHXQ/pGzMrH0IjQ",
        "srcdb": "202120"
    },
    {
        "key": "8945",
        "code": "EEPS 1330",
        "title": "Global Environmental Remote Sensing",
        "crn": "26064",
        "no": "S01",
        "total": "1",
        "schd": "S",
        "stat": "F",
        "hide": "",
        "isCancelled": "",
        "meets": "MWF 2-2:50p",
        "mpkey": "2053",
        "meetingTimes": "[{\"meet_day\":\"0\",\"start_time\":\"1400\",\"end_time\":\"1450\"},{\"meet_day\":\"2\",\"start_time\":\"1400\",\"end_time\":\"1450\"},{\"meet_day\":\"4\",\"start_time\":\"1400\",\"end_time\":\"1450\"}]",
        "instr": "J. Mustard",
        "start_date": "2022-01-26",
        "end_date": "2022-05-20",
        "permreq": "N",
        "rpt": "N",
        "open_enroll": "",
        "acad_career": "",
        "cart_opts": "{\"grade_mode\":{\"cart_field\":\"p_gmod\",\"enabled\":true,\"options\":[{\"value\":\"G\",\"label\":\"Standard ABC/No Credit\",\"default\":true,\"selected\":\"selected\"},{\"value\":\"A\",\"label\":\"Audit\",\"default\":false,\"selected\":\"\"},{\"value\":\"S\",\"label\":\"Satisfactory/No Credit\",\"default\":false,\"selected\":\"\"}]},\"credit_hrs\":{\"cartField\":\"p_hours\",\"enabled\":true,\"options\":[{\"value\":\"1\",\"label\":\"1\",\"default\":true,\"selected\":\"selected\"}]},\"swap_section_with\":{\"enabled\":true,\"options\":[{\"value\":\"\",\"label\":\"Not Applicable\",\"default\":true,\"selected\":\"selected\"}]}}",
        "linked_crns": "",
        "auto_enroll_sections": "",
        "is_enroll_section": "",
        "rfam": "2154",
        "lrfam": "",
        "changehash": "58tzheb2Slb9KfuuhDQmOQ",
        "srcdb": "202120"
    },
    {
        "key": "8946",
        "code": "EEPS 1370",
        "title": "Environmental Geochemistry",
        "crn": "26975",
        "no": "S01",
        "total": "1",
        "schd": "S",
        "stat": "A",
        "hide": "",
        "isCancelled": "",
        "meets": "TTh 9-10:20a",
        "mpkey": "2023",
        "meetingTimes": "[{\"meet_day\":\"1\",\"start_time\":\"900\",\"end_time\":\"1020\"},{\"meet_day\":\"3\",\"start_time\":\"900\",\"end_time\":\"1020\"}]",
        "instr": "Y. Huang",
        "start_date": "2022-01-26",
        "end_date": "2022-05-20",
        "permreq": "N",
        "rpt": "N",
        "open_enroll": "",
        "acad_career": "",
        "cart_opts": "{\"grade_mode\":{\"cart_field\":\"p_gmod\",\"enabled\":true,\"options\":[{\"value\":\"G\",\"label\":\"Standard ABC/No Credit\",\"default\":true,\"selected\":\"selected\"},{\"value\":\"A\",\"label\":\"Audit\",\"default\":false,\"selected\":\"\"},{\"value\":\"S\",\"label\":\"Satisfactory/No Credit\",\"default\":false,\"selected\":\"\"}]},\"credit_hrs\":{\"cartField\":\"p_hours\",\"enabled\":true,\"options\":[{\"value\":\"1\",\"label\":\"1\",\"default\":true,\"selected\":\"selected\"}]},\"swap_section_with\":{\"enabled\":true,\"options\":[{\"value\":\"\",\"label\":\"Not Applicable\",\"default\":true,\"selected\":\"selected\"}]}}",
        "linked_crns": "",
        "auto_enroll_sections": "",
        "is_enroll_section": "",
        "rfam": "2780",
        "lrfam": "",
        "changehash": "GO2UKBEAwm5hR1qhut0YvA",
        "srcdb": "202120"
    },
    {
        "key": "2515",
        "code": "EEPS 1410",
        "title": "Mineralogy",
        "crn": "16885",
        "no": "S01",
        "total": "1",
        "schd": "S",
        "stat": "A",
        "hide": "",
        "isCancelled": "",
        "meets": "MWF 11-11:50a",
        "mpkey": "2044",
        "meetingTimes": "[{\"meet_day\":\"0\",\"start_time\":\"1100\",\"end_time\":\"1150\"},{\"meet_day\":\"2\",\"start_time\":\"1100\",\"end_time\":\"1150\"},{\"meet_day\":\"4\",\"start_time\":\"1100\",\"end_time\":\"1150\"}]",
        "instr": "R. Cooper",
        "start_date": "2021-09-08",
        "end_date": "2021-12-21",
        "permreq": "N",
        "rpt": "N",
        "open_enroll": "",
        "acad_career": "",
        "cart_opts": "{\"grade_mode\":{\"cart_field\":\"p_gmod\",\"enabled\":true,\"options\":[{\"value\":\"G\",\"label\":\"Standard ABC/No Credit\",\"default\":true,\"selected\":\"selected\"},{\"value\":\"A\",\"label\":\"Audit\",\"default\":false,\"selected\":\"\"},{\"value\":\"S\",\"label\":\"Satisfactory/No Credit\",\"default\":false,\"selected\":\"\"}]},\"credit_hrs\":{\"cartField\":\"p_hours\",\"enabled\":true,\"options\":[{\"value\":\"1\",\"label\":\"1\",\"default\":true,\"selected\":\"selected\"}]},\"swap_section_with\":{\"enabled\":true,\"options\":[{\"value\":\"\",\"label\":\"Not Applicable\",\"default\":true,\"selected\":\"selected\"}]}}",
        "linked_crns": "",
        "auto_enroll_sections": "",
        "is_enroll_section": "",
        "rfam": "2302",
        "lrfam": "",
        "changehash": "gvg9XVSGba85wb7IhSIr1g",
        "srcdb": "202110"
    },
    {
        "key": "8948",
        "code": "EEPS 1510",
        "title": "Introduction to Atmospheric Dynamics",
        "crn": "26945",
        "no": "S01",
        "total": "1",
        "schd": "S",
        "stat": "A",
        "hide": "",
        "isCancelled": "",
        "meets": "TTh 1-2:20p",
        "mpkey": "2020",
        "meetingTimes": "[{\"meet_day\":\"1\",\"start_time\":\"1300\",\"end_time\":\"1420\"},{\"meet_day\":\"3\",\"start_time\":\"1300\",\"end_time\":\"1420\"}]",
        "instr": "A. Lynch",
        "start_date": "2022-01-26",
        "end_date": "2022-05-20",
        "permreq": "N",
        "rpt": "N",
        "open_enroll": "",
        "acad_career": "",
        "cart_opts": "{\"grade_mode\":{\"cart_field\":\"p_gmod\",\"enabled\":true,\"options\":[{\"value\":\"G\",\"label\":\"Standard ABC/No Credit\",\"default\":true,\"selected\":\"selected\"},{\"value\":\"A\",\"label\":\"Audit\",\"default\":false,\"selected\":\"\"},{\"value\":\"S\",\"label\":\"Satisfactory/No Credit\",\"default\":false,\"selected\":\"\"}]},\"credit_hrs\":{\"cartField\":\"p_hours\",\"enabled\":true,\"options\":[{\"value\":\"1\",\"label\":\"1\",\"default\":true,\"selected\":\"selected\"}]},\"swap_section_with\":{\"enabled\":true,\"options\":[{\"value\":\"\",\"label\":\"Not Applicable\",\"default\":true,\"selected\":\"selected\"}]}}",
        "linked_crns": "",
        "auto_enroll_sections": "",
        "is_enroll_section": "",
        "rfam": "2776",
        "lrfam": "",
        "changehash": "FJJnUq42dvI2ZqVDryHdKA",
        "srcdb": "202120"
    },
    {
        "key": "8949",
        "code": "EEPS 1560",
        "title": "Global Tectonics",
        "crn": "26073",
        "no": "S01",
        "total": "1",
        "schd": "S",
        "stat": "A",
        "hide": "",
        "isCancelled": "",
        "meets": "TTh 10:30-11:50a",
        "mpkey": "2026",
        "meetingTimes": "[{\"meet_day\":\"1\",\"start_time\":\"1030\",\"end_time\":\"1150\"},{\"meet_day\":\"3\",\"start_time\":\"1030\",\"end_time\":\"1150\"}]",
        "instr": "Team",
        "start_date": "2022-01-26",
        "end_date": "2022-05-20",
        "permreq": "N",
        "rpt": "N",
        "open_enroll": "",
        "acad_career": "",
        "cart_opts": "{\"grade_mode\":{\"cart_field\":\"p_gmod\",\"enabled\":true,\"options\":[{\"value\":\"G\",\"label\":\"Standard ABC/No Credit\",\"default\":true,\"selected\":\"selected\"},{\"value\":\"A\",\"label\":\"Audit\",\"default\":false,\"selected\":\"\"},{\"value\":\"S\",\"label\":\"Satisfactory/No Credit\",\"default\":false,\"selected\":\"\"}]},\"credit_hrs\":{\"cartField\":\"p_hours\",\"enabled\":true,\"options\":[{\"value\":\"1\",\"label\":\"1\",\"default\":true,\"selected\":\"selected\"}]},\"swap_section_with\":{\"enabled\":true,\"options\":[{\"value\":\"\",\"label\":\"Not Applicable\",\"default\":true,\"selected\":\"selected\"}]}}",
        "linked_crns": "",
        "auto_enroll_sections": "",
        "is_enroll_section": "",
        "rfam": "2640",
        "lrfam": "",
        "changehash": "WKgjmXClxhREuqs82N+CPg",
        "srcdb": "202120"
    },
    {
        "key": "2516",
        "code": "EEPS 1610",
        "title": "Solid Earth Geophysics",
        "crn": "17687",
        "no": "S01",
        "total": "1",
        "schd": "S",
        "stat": "A",
        "hide": "",
        "isCancelled": "",
        "meets": "TTh 1-2:20p",
        "mpkey": "2020",
        "meetingTimes": "[{\"meet_day\":\"1\",\"start_time\":\"1300\",\"end_time\":\"1420\"},{\"meet_day\":\"3\",\"start_time\":\"1300\",\"end_time\":\"1420\"}]",
        "instr": "C. Dalton",
        "start_date": "2021-09-08",
        "end_date": "2021-12-21",
        "permreq": "N",
        "rpt": "N",
        "open_enroll": "",
        "acad_career": "",
        "cart_opts": "{\"grade_mode\":{\"cart_field\":\"p_gmod\",\"enabled\":true,\"options\":[{\"value\":\"G\",\"label\":\"Standard ABC/No Credit\",\"default\":true,\"selected\":\"selected\"},{\"value\":\"A\",\"label\":\"Audit\",\"default\":false,\"selected\":\"\"},{\"value\":\"S\",\"label\":\"Satisfactory/No Credit\",\"default\":false,\"selected\":\"\"}]},\"credit_hrs\":{\"cartField\":\"p_hours\",\"enabled\":true,\"options\":[{\"value\":\"1\",\"label\":\"1\",\"default\":true,\"selected\":\"selected\"}]},\"swap_section_with\":{\"enabled\":true,\"options\":[{\"value\":\"\",\"label\":\"Not Applicable\",\"default\":true,\"selected\":\"selected\"}]}}",
        "linked_crns": "",
        "auto_enroll_sections": "",
        "is_enroll_section": "",
        "rfam": "2154",
        "lrfam": "",
        "changehash": "6Lh2aDAk4I+BX0a0o3Gx5Q",
        "srcdb": "202110"
    },
    {
        "key": "2517",
        "code": "EEPS 1615",
        "title": "The Environmental Policy Process",
        "crn": "17694",
        "no": "S01",
        "total": "1",
        "schd": "S",
        "stat": "A",
        "hide": "",
        "isCancelled": "",
        "meets": "TTh 2:30-3:50p",
        "mpkey": "2035",
        "meetingTimes": "[{\"meet_day\":\"1\",\"start_time\":\"1430\",\"end_time\":\"1550\"},{\"meet_day\":\"3\",\"start_time\":\"1430\",\"end_time\":\"1550\"}]",
        "instr": "A. Lynch",
        "start_date": "2021-09-08",
        "end_date": "2021-12-21",
        "permreq": "Y",
        "rpt": "N",
        "open_enroll": "",
        "acad_career": "",
        "cart_opts": "{\"grade_mode\":{\"cart_field\":\"p_gmod\",\"enabled\":true,\"options\":[{\"value\":\"G\",\"label\":\"Standard ABC/No Credit\",\"default\":true,\"selected\":\"selected\"},{\"value\":\"A\",\"label\":\"Audit\",\"default\":false,\"selected\":\"\"},{\"value\":\"S\",\"label\":\"Satisfactory/No Credit\",\"default\":false,\"selected\":\"\"}]},\"credit_hrs\":{\"cartField\":\"p_hours\",\"enabled\":true,\"options\":[{\"value\":\"1\",\"label\":\"1\",\"default\":true,\"selected\":\"selected\"}]},\"swap_section_with\":{\"enabled\":true,\"options\":[{\"value\":\"\",\"label\":\"Not Applicable\",\"default\":true,\"selected\":\"selected\"}]}}",
        "linked_crns": "",
        "auto_enroll_sections": "",
        "is_enroll_section": "",
        "rfam": "2154",
        "lrfam": "",
        "changehash": "OmitaasRQ44vy7hCuc3c2A",
        "srcdb": "202110"
    },
    {
        "key": "8950",
        "code": "EEPS 1620",
        "title": "Continuum Physics of the Solid Earth",
        "crn": "26074",
        "no": "S01",
        "total": "1",
        "schd": "S",
        "stat": "A",
        "hide": "",
        "isCancelled": "",
        "meets": "TTh 2:30-3:50p",
        "mpkey": "2035",
        "meetingTimes": "[{\"meet_day\":\"1\",\"start_time\":\"1430\",\"end_time\":\"1550\"},{\"meet_day\":\"3\",\"start_time\":\"1430\",\"end_time\":\"1550\"}]",
        "instr": "Huber/Tsai",
        "start_date": "2022-01-26",
        "end_date": "2022-05-20",
        "permreq": "N",
        "rpt": "N",
        "open_enroll": "",
        "acad_career": "",
        "cart_opts": "{\"grade_mode\":{\"cart_field\":\"p_gmod\",\"enabled\":true,\"options\":[{\"value\":\"G\",\"label\":\"Standard ABC/No Credit\",\"default\":true,\"selected\":\"selected\"},{\"value\":\"A\",\"label\":\"Audit\",\"default\":false,\"selected\":\"\"},{\"value\":\"S\",\"label\":\"Satisfactory/No Credit\",\"default\":false,\"selected\":\"\"}]},\"credit_hrs\":{\"cartField\":\"p_hours\",\"enabled\":true,\"options\":[{\"value\":\"1\",\"label\":\"1\",\"default\":true,\"selected\":\"selected\"}]},\"swap_section_with\":{\"enabled\":true,\"options\":[{\"value\":\"\",\"label\":\"Not Applicable\",\"default\":true,\"selected\":\"selected\"}]}}",
        "linked_crns": "",
        "auto_enroll_sections": "",
        "is_enroll_section": "",
        "rfam": "2154",
        "lrfam": "",
        "changehash": "zsB9f62tdw/sFAiZmYQQSg",
        "srcdb": "202120"
    },
    {
        "key": "2518",
        "code": "EEPS 1630",
        "title": "Introduction to Quantitative Glaciology",
        "crn": "16891",
        "no": "S01",
        "total": "1",
        "schd": "S",
        "stat": "A",
        "hide": "",
        "isCancelled": "",
        "meets": "TTh 1-2:20p",
        "mpkey": "2020",
        "meetingTimes": "[{\"meet_day\":\"1\",\"start_time\":\"1300\",\"end_time\":\"1420\"},{\"meet_day\":\"3\",\"start_time\":\"1300\",\"end_time\":\"1420\"}]",
        "instr": "V. Tsai",
        "start_date": "2021-09-08",
        "end_date": "2021-12-21",
        "permreq": "N",
        "rpt": "N",
        "open_enroll": "",
        "acad_career": "",
        "cart_opts": "{\"grade_mode\":{\"cart_field\":\"p_gmod\",\"enabled\":true,\"options\":[{\"value\":\"G\",\"label\":\"Standard ABC/No Credit\",\"default\":true,\"selected\":\"selected\"},{\"value\":\"A\",\"label\":\"Audit\",\"default\":false,\"selected\":\"\"},{\"value\":\"S\",\"label\":\"Satisfactory/No Credit\",\"default\":false,\"selected\":\"\"}]},\"credit_hrs\":{\"cartField\":\"p_hours\",\"enabled\":true,\"options\":[{\"value\":\"1\",\"label\":\"1\",\"default\":true,\"selected\":\"selected\"}]},\"swap_section_with\":{\"enabled\":true,\"options\":[{\"value\":\"\",\"label\":\"Not Applicable\",\"default\":true,\"selected\":\"selected\"}]}}",
        "linked_crns": "",
        "auto_enroll_sections": "",
        "is_enroll_section": "",
        "rfam": "2303",
        "lrfam": "",
        "changehash": "jva9xEwPV9A7Ae7mpraTzg",
        "srcdb": "202110"
    },
    {
        "key": "8951",
        "code": "EEPS 1960C",
        "title": "Planetary Petrology",
        "crn": "27038",
        "no": "S01",
        "total": "1",
        "schd": "S",
        "stat": "A",
        "hide": "",
        "isCancelled": "",
        "meets": "TTh 1-2:20p",
        "mpkey": "2020",
        "meetingTimes": "[{\"meet_day\":\"1\",\"start_time\":\"1300\",\"end_time\":\"1420\"},{\"meet_day\":\"3\",\"start_time\":\"1300\",\"end_time\":\"1420\"}]",
        "instr": "Y. Liang",
        "start_date": "2022-01-26",
        "end_date": "2022-05-20",
        "permreq": "N",
        "rpt": "N",
        "open_enroll": "",
        "acad_career": "",
        "cart_opts": "{\"grade_mode\":{\"cart_field\":\"p_gmod\",\"enabled\":true,\"options\":[{\"value\":\"G\",\"label\":\"Standard ABC/No Credit\",\"default\":true,\"selected\":\"selected\"},{\"value\":\"A\",\"label\":\"Audit\",\"default\":false,\"selected\":\"\"},{\"value\":\"S\",\"label\":\"Satisfactory/No Credit\",\"default\":false,\"selected\":\"\"}]},\"credit_hrs\":{\"cartField\":\"p_hours\",\"enabled\":true,\"options\":[{\"value\":\"1\",\"label\":\"1\",\"default\":true,\"selected\":\"selected\"}]},\"swap_section_with\":{\"enabled\":true,\"options\":[{\"value\":\"\",\"label\":\"Not Applicable\",\"default\":true,\"selected\":\"selected\"}]}}",
        "linked_crns": "",
        "auto_enroll_sections": "",
        "is_enroll_section": "",
        "rfam": "2785",
        "lrfam": "",
        "changehash": "PNoR3qNNMjmxpj9BNPibPg",
        "srcdb": "202120"
    },
    {
        "key": "8952",
        "code": "EEPS 1960D",
        "title": "Machine Learning for the Earth and Environment",
        "crn": "27360",
        "no": "S01",
        "total": "1",
        "schd": "S",
        "stat": "F",
        "hide": "",
        "isCancelled": "",
        "meets": "TTh 2:30-3:50p",
        "mpkey": "2035",
        "meetingTimes": "[{\"meet_day\":\"1\",\"start_time\":\"1430\",\"end_time\":\"1550\"},{\"meet_day\":\"3\",\"start_time\":\"1430\",\"end_time\":\"1550\"}]",
        "instr": "K. Bergen",
        "start_date": "2022-01-26",
        "end_date": "2022-05-20",
        "permreq": "Y",
        "rpt": "N",
        "open_enroll": "",
        "acad_career": "",
        "cart_opts": "{\"grade_mode\":{\"cart_field\":\"p_gmod\",\"enabled\":true,\"options\":[{\"value\":\"G\",\"label\":\"Standard ABC/No Credit\",\"default\":true,\"selected\":\"selected\"},{\"value\":\"A\",\"label\":\"Audit\",\"default\":false,\"selected\":\"\"},{\"value\":\"S\",\"label\":\"Satisfactory/No Credit\",\"default\":false,\"selected\":\"\"}]},\"credit_hrs\":{\"cartField\":\"p_hours\",\"enabled\":true,\"options\":[{\"value\":\"1\",\"label\":\"1\",\"default\":true,\"selected\":\"selected\"}]},\"swap_section_with\":{\"enabled\":true,\"options\":[{\"value\":\"\",\"label\":\"Not Applicable\",\"default\":true,\"selected\":\"selected\"}]}}",
        "linked_crns": "",
        "auto_enroll_sections": "",
        "is_enroll_section": "",
        "rfam": "2154",
        "lrfam": "",
        "changehash": "huiPwxVhQD/xzeJ+n4MjOQ",
        "srcdb": "202120"
    },
    {
        "key": "8953",
        "code": "EEPS 1960F",
        "title": "Patterns in Nature, in Society",
        "crn": "26976",
        "no": "S01",
        "total": "1",
        "schd": "S",
        "stat": "A",
        "hide": "",
        "isCancelled": "",
        "meets": "TTh 2:30-3:50p",
        "mpkey": "2035",
        "meetingTimes": "[{\"meet_day\":\"1\",\"start_time\":\"1430\",\"end_time\":\"1550\"},{\"meet_day\":\"3\",\"start_time\":\"1430\",\"end_time\":\"1550\"}]",
        "instr": "R. Cooper",
        "start_date": "2022-01-26",
        "end_date": "2022-05-20",
        "permreq": "Y",
        "rpt": "N",
        "open_enroll": "",
        "acad_career": "",
        "cart_opts": "{\"grade_mode\":{\"cart_field\":\"p_gmod\",\"enabled\":true,\"options\":[{\"value\":\"G\",\"label\":\"Standard ABC/No Credit\",\"default\":true,\"selected\":\"selected\"},{\"value\":\"A\",\"label\":\"Audit\",\"default\":false,\"selected\":\"\"},{\"value\":\"S\",\"label\":\"Satisfactory/No Credit\",\"default\":false,\"selected\":\"\"}]},\"credit_hrs\":{\"cartField\":\"p_hours\",\"enabled\":true,\"options\":[{\"value\":\"1\",\"label\":\"1\",\"default\":true,\"selected\":\"selected\"}]},\"swap_section_with\":{\"enabled\":true,\"options\":[{\"value\":\"\",\"label\":\"Not Applicable\",\"default\":true,\"selected\":\"selected\"}]}}",
        "linked_crns": "",
        "auto_enroll_sections": "",
        "is_enroll_section": "",
        "rfam": "2154",
        "lrfam": "",
        "changehash": "cf8ur6jKA/dMDRc9OHaz0g",
        "srcdb": "202120"
    },
    {
        "key": "8956",
        "code": "EEPS 1960X",
        "title": "Ocean, Cryosphere, and Sea Level Change",
        "crn": "27358",
        "no": "S01",
        "total": "1",
        "schd": "S",
        "stat": "A",
        "hide": "",
        "isCancelled": "",
        "meets": "TTh 9-10:20a",
        "mpkey": "2023",
        "meetingTimes": "[{\"meet_day\":\"1\",\"start_time\":\"900\",\"end_time\":\"1020\"},{\"meet_day\":\"3\",\"start_time\":\"900\",\"end_time\":\"1020\"}]",
        "instr": "B. Fox-Kemper",
        "start_date": "2022-01-26",
        "end_date": "2022-05-20",
        "permreq": "N",
        "rpt": "N",
        "open_enroll": "",
        "acad_career": "",
        "cart_opts": "{\"grade_mode\":{\"cart_field\":\"p_gmod\",\"enabled\":true,\"options\":[{\"value\":\"G\",\"label\":\"Standard ABC/No Credit\",\"default\":true,\"selected\":\"selected\"},{\"value\":\"A\",\"label\":\"Audit\",\"default\":false,\"selected\":\"\"},{\"value\":\"S\",\"label\":\"Satisfactory/No Credit\",\"default\":false,\"selected\":\"\"}]},\"credit_hrs\":{\"cartField\":\"p_hours\",\"enabled\":true,\"options\":[{\"value\":\"1\",\"label\":\"1\",\"default\":true,\"selected\":\"selected\"}]},\"swap_section_with\":{\"enabled\":true,\"options\":[{\"value\":\"\",\"label\":\"Not Applicable\",\"default\":true,\"selected\":\"selected\"}]}}",
        "linked_crns": "",
        "auto_enroll_sections": "",
        "is_enroll_section": "",
        "rfam": "2826",
        "lrfam": "",
        "changehash": "INQmYe62E7Pomi7qVoBMBw",
        "srcdb": "202120"
    },
    {
        "key": "2549",
        "code": "EEPS 2300",
        "title": "Mathematical and Computational Earth Sciences",
        "crn": "17682",
        "no": "S01",
        "total": "3",
        "schd": "S",
        "stat": "A",
        "hide": "",
        "isCancelled": "",
        "meets": "MW 4-5:20p",
        "mpkey": "2712",
        "meetingTimes": "[{\"meet_day\":\"0\",\"start_time\":\"1600\",\"end_time\":\"1720\"},{\"meet_day\":\"2\",\"start_time\":\"1600\",\"end_time\":\"1720\"}]",
        "instr": "B. Fox-Kemper",
        "start_date": "2021-09-08",
        "end_date": "2021-12-21",
        "permreq": "N",
        "rpt": "N",
        "open_enroll": "",
        "acad_career": "",
        "cart_opts": "{\"grade_mode\":{\"cart_field\":\"p_gmod\",\"enabled\":true,\"options\":[{\"value\":\"G\",\"label\":\"Standard ABC/No Credit\",\"default\":true,\"selected\":\"selected\"},{\"value\":\"A\",\"label\":\"Audit\",\"default\":false,\"selected\":\"\"},{\"value\":\"S\",\"label\":\"Satisfactory/No Credit\",\"default\":false,\"selected\":\"\"}]},\"credit_hrs\":{\"cartField\":\"p_hours\",\"enabled\":true,\"options\":[{\"value\":\"1\",\"label\":\"1\",\"default\":true,\"selected\":\"selected\"}]},\"swap_section_with\":{\"enabled\":true,\"options\":[{\"value\":\"\",\"label\":\"Not Applicable\",\"default\":true,\"selected\":\"selected\"}]}}",
        "linked_crns": "",
        "auto_enroll_sections": "",
        "is_enroll_section": "",
        "rfam": "2156",
        "lrfam": "",
        "changehash": "BazxPLbfwwCL3ufAM+ajCA",
        "srcdb": "202110"
    },
    {
        "key": "2552",
        "code": "EEPS 2840",
        "title": "Asteroids and Meteorites",
        "crn": "16881",
        "no": "S02",
        "total": "1",
        "schd": "S",
        "stat": "A",
        "hide": "",
        "isCancelled": "",
        "meets": "TTh 10:30-11:50a",
        "mpkey": "2026",
        "meetingTimes": "[{\"meet_day\":\"1\",\"start_time\":\"1030\",\"end_time\":\"1150\"},{\"meet_day\":\"3\",\"start_time\":\"1030\",\"end_time\":\"1150\"}]",
        "instr": "R. Milliken",
        "start_date": "2021-09-08",
        "end_date": "2021-12-21",
        "permreq": "N",
        "rpt": "N",
        "open_enroll": "",
        "acad_career": "",
        "cart_opts": "{\"grade_mode\":{\"cart_field\":\"p_gmod\",\"enabled\":true,\"options\":[{\"value\":\"G\",\"label\":\"Standard ABC/No Credit\",\"default\":true,\"selected\":\"selected\"},{\"value\":\"A\",\"label\":\"Audit\",\"default\":false,\"selected\":\"\"},{\"value\":\"S\",\"label\":\"Satisfactory/No Credit\",\"default\":false,\"selected\":\"\"}]},\"credit_hrs\":{\"cartField\":\"p_hours\",\"enabled\":true,\"options\":[{\"value\":\"1\",\"label\":\"1\",\"default\":true,\"selected\":\"selected\"}]},\"swap_section_with\":{\"enabled\":true,\"options\":[{\"value\":\"\",\"label\":\"Not Applicable\",\"default\":true,\"selected\":\"selected\"}]}}",
        "linked_crns": "",
        "auto_enroll_sections": "",
        "is_enroll_section": "",
        "rfam": "2154",
        "lrfam": "",
        "changehash": "REjMU4cf6Qxo1v1gJ6cMiA",
        "srcdb": "202110"
    },
    {
        "key": "8989",
        "code": "EEPS 2910H",
        "title": "Geophysical Phenomena Across the Solar System",
        "crn": "27267",
        "no": "S01",
        "total": "1",
        "schd": "S",
        "stat": "A",
        "hide": "",
        "isCancelled": "",
        "meets": "TTh 10:30-11:50a",
        "mpkey": "2026",
        "meetingTimes": "[{\"meet_day\":\"1\",\"start_time\":\"1030\",\"end_time\":\"1150\"},{\"meet_day\":\"3\",\"start_time\":\"1030\",\"end_time\":\"1150\"}]",
        "instr": "A. Evans",
        "start_date": "2022-01-26",
        "end_date": "2022-05-20",
        "permreq": "N",
        "rpt": "N",
        "open_enroll": "",
        "acad_career": "",
        "cart_opts": "{\"grade_mode\":{\"cart_field\":\"p_gmod\",\"enabled\":true,\"options\":[{\"value\":\"G\",\"label\":\"Standard ABC/No Credit\",\"default\":true,\"selected\":\"selected\"},{\"value\":\"A\",\"label\":\"Audit\",\"default\":false,\"selected\":\"\"},{\"value\":\"S\",\"label\":\"Satisfactory/No Credit\",\"default\":false,\"selected\":\"\"}]},\"credit_hrs\":{\"cartField\":\"p_hours\",\"enabled\":true,\"options\":[{\"value\":\"1\",\"label\":\"1\",\"default\":true,\"selected\":\"selected\"}]},\"swap_section_with\":{\"enabled\":true,\"options\":[{\"value\":\"\",\"label\":\"Not Applicable\",\"default\":true,\"selected\":\"selected\"}]}}",
        "linked_crns": "",
        "auto_enroll_sections": "",
        "is_enroll_section": "",
        "rfam": "2156",
        "lrfam": "",
        "changehash": "zpDkjP/l6NtwQ+95Iz9wug",
        "srcdb": "202120"
    },
    {
        "key": "2553",
        "code": "EEPS 2910T",
        "title": "Lattice Boltzmann Modeling in Natural Sciences",
        "crn": "18039",
        "no": "S01",
        "total": "1",
        "schd": "S",
        "stat": "A",
        "hide": "",
        "isCancelled": "",
        "meets": "TTh 2:30-3:50p",
        "mpkey": "2035",
        "meetingTimes": "[{\"meet_day\":\"1\",\"start_time\":\"1430\",\"end_time\":\"1550\"},{\"meet_day\":\"3\",\"start_time\":\"1430\",\"end_time\":\"1550\"}]",
        "instr": "C. Huber",
        "start_date": "2021-09-08",
        "end_date": "2021-12-21",
        "permreq": "N",
        "rpt": "N",
        "open_enroll": "",
        "acad_career": "",
        "cart_opts": "{\"grade_mode\":{\"cart_field\":\"p_gmod\",\"enabled\":true,\"options\":[{\"value\":\"G\",\"label\":\"Standard ABC/No Credit\",\"default\":true,\"selected\":\"selected\"},{\"value\":\"A\",\"label\":\"Audit\",\"default\":false,\"selected\":\"\"},{\"value\":\"S\",\"label\":\"Satisfactory/No Credit\",\"default\":false,\"selected\":\"\"}]},\"credit_hrs\":{\"cartField\":\"p_hours\",\"enabled\":true,\"options\":[{\"value\":\"1\",\"label\":\"1\",\"default\":true,\"selected\":\"selected\"}]},\"swap_section_with\":{\"enabled\":true,\"options\":[{\"value\":\"\",\"label\":\"Not Applicable\",\"default\":true,\"selected\":\"selected\"}]}}",
        "linked_crns": "",
        "auto_enroll_sections": "",
        "is_enroll_section": "",
        "rfam": "2156",
        "lrfam": "",
        "changehash": "4v2pK4IGSZ5eZCAOiIrVOw",
        "srcdb": "202110"
    },
    {
        "key": "2554",
        "code": "EEPS 2910Z",
        "title": "Trace Element Geochemistry",
        "crn": "16883",
        "no": "S01",
        "total": "1",
        "schd": "S",
        "stat": "A",
        "hide": "",
        "isCancelled": "",
        "meets": "MW 1-2:20p",
        "mpkey": "2253",
        "meetingTimes": "[{\"meet_day\":\"0\",\"start_time\":\"1300\",\"end_time\":\"1420\"},{\"meet_day\":\"2\",\"start_time\":\"1300\",\"end_time\":\"1420\"}]",
        "instr": "Y. Liang",
        "start_date": "2021-09-08",
        "end_date": "2021-12-21",
        "permreq": "N",
        "rpt": "N",
        "open_enroll": "",
        "acad_career": "",
        "cart_opts": "{\"grade_mode\":{\"cart_field\":\"p_gmod\",\"enabled\":true,\"options\":[{\"value\":\"G\",\"label\":\"Standard ABC/No Credit\",\"default\":true,\"selected\":\"selected\"},{\"value\":\"A\",\"label\":\"Audit\",\"default\":false,\"selected\":\"\"},{\"value\":\"S\",\"label\":\"Satisfactory/No Credit\",\"default\":false,\"selected\":\"\"}]},\"credit_hrs\":{\"cartField\":\"p_hours\",\"enabled\":true,\"options\":[{\"value\":\"1\",\"label\":\"1\",\"default\":true,\"selected\":\"selected\"}]},\"swap_section_with\":{\"enabled\":true,\"options\":[{\"value\":\"\",\"label\":\"Not Applicable\",\"default\":true,\"selected\":\"selected\"}]}}",
        "linked_crns": "",
        "auto_enroll_sections": "",
        "is_enroll_section": "",
        "rfam": "2304",
        "lrfam": "",
        "changehash": "TSFgV1ogR8Uif+qlAJpkcA",
        "srcdb": "202110"
    },
    {
        "key": "8990",
        "code": "EEPS 2920A",
        "title": "Measuring Climate and Environmental Change with Geophysical Data",
        "crn": "27171",
        "no": "S01",
        "total": "1",
        "schd": "S",
        "stat": "F",
        "hide": "",
        "isCancelled": "",
        "meets": "TTh 1-2:20p",
        "mpkey": "2020",
        "meetingTimes": "[{\"meet_day\":\"1\",\"start_time\":\"1300\",\"end_time\":\"1420\"},{\"meet_day\":\"3\",\"start_time\":\"1300\",\"end_time\":\"1420\"}]",
        "instr": "Fischer/Dalton",
        "start_date": "2022-01-26",
        "end_date": "2022-05-20",
        "permreq": "N",
        "rpt": "N",
        "open_enroll": "",
        "acad_career": "",
        "cart_opts": "{\"grade_mode\":{\"cart_field\":\"p_gmod\",\"enabled\":true,\"options\":[{\"value\":\"G\",\"label\":\"Standard ABC/No Credit\",\"default\":true,\"selected\":\"selected\"},{\"value\":\"A\",\"label\":\"Audit\",\"default\":false,\"selected\":\"\"},{\"value\":\"S\",\"label\":\"Satisfactory/No Credit\",\"default\":false,\"selected\":\"\"}]},\"credit_hrs\":{\"cartField\":\"p_hours\",\"enabled\":true,\"options\":[{\"value\":\"1\",\"label\":\"1\",\"default\":true,\"selected\":\"selected\"}]},\"swap_section_with\":{\"enabled\":true,\"options\":[{\"value\":\"\",\"label\":\"Not Applicable\",\"default\":true,\"selected\":\"selected\"}]}}",
        "linked_crns": "",
        "auto_enroll_sections": "",
        "is_enroll_section": "",
        "rfam": "2154",
        "lrfam": "",
        "changehash": "PwqRsAloYv3IDlv7Egrmcg",
        "srcdb": "202120"
    },
    {
        "key": "2584",
        "code": "EEPS 2990",
        "title": "Thesis Preparation",
        "crn": "15698",
        "no": "S01",
        "total": "2",
        "schd": "E",
        "stat": "A",
        "hide": "",
        "isCancelled": "",
        "meets": "TBA",
        "mpkey": "1",
        "meetingTimes": "[]",
        "instr": "TBD",
        "start_date": "2021-09-08",
        "end_date": "2021-12-21",
        "permreq": "N",
        "rpt": "Y",
        "open_enroll": "",
        "acad_career": "",
        "cart_opts": "{\"grade_mode\":{\"cart_field\":\"p_gmod\",\"enabled\":true,\"options\":[{\"value\":\"N\",\"label\":\"No Credit/Gradable\",\"default\":true,\"selected\":\"selected\"}]},\"credit_hrs\":{\"cartField\":\"p_hours\",\"enabled\":true,\"options\":[{\"value\":\"0\",\"label\":\"0\",\"default\":true,\"selected\":\"selected\"}]},\"swap_section_with\":{\"enabled\":true,\"options\":[{\"value\":\"\",\"label\":\"Not Applicable\",\"default\":true,\"selected\":\"selected\"}]}}",
        "linked_crns": "",
        "auto_enroll_sections": "",
        "is_enroll_section": "",
        "rfam": "2305",
        "lrfam": "",
        "changehash": "1B2M2Y8AsgTpgAmY7PhCfg",
        "srcdb": "202110"
    },
    {
        "key": "9021",
        "code": "EEPS 2990",
        "title": "Thesis Preparation",
        "crn": "24579",
        "no": "S01",
        "total": "2",
        "schd": "E",
        "stat": "A",
        "hide": "",
        "isCancelled": "",
        "meets": "TBA",
        "mpkey": "1",
        "meetingTimes": "[]",
        "instr": "TBD",
        "start_date": "2022-01-26",
        "end_date": "2022-05-20",
        "permreq": "N",
        "rpt": "Y",
        "open_enroll": "",
        "acad_career": "",
        "cart_opts": "{\"grade_mode\":{\"cart_field\":\"p_gmod\",\"enabled\":true,\"options\":[{\"value\":\"N\",\"label\":\"No Credit/Gradable\",\"default\":true,\"selected\":\"selected\"}]},\"credit_hrs\":{\"cartField\":\"p_hours\",\"enabled\":true,\"options\":[{\"value\":\"0\",\"label\":\"0\",\"default\":true,\"selected\":\"selected\"}]},\"swap_section_with\":{\"enabled\":true,\"options\":[{\"value\":\"\",\"label\":\"Not Applicable\",\"default\":true,\"selected\":\"selected\"}]}}",
        "linked_crns": "",
        "auto_enroll_sections": "",
        "is_enroll_section": "",
        "rfam": "2305",
        "lrfam": "",
        "changehash": "1B2M2Y8AsgTpgAmY7PhCfg",
        "srcdb": "202120"
    }
]