[
    {
        "code": "EMOW 0062",
        "title": "Dutch and Flemish Art:  Visual Culture of the Netherlands in the Seventeenth Century (HIAA 0062)",
        "semesters": [
            "Fall"
        ],
        "crn": "18060"
    },
    {
        "code": "EMOW 0081",
        "title": "Architecture of the House Through Space and Time (HIAA 0081)",
        "semesters": [
            "Fall"
        ],
        "crn": "17809"
    },
    {
        "code": "EMOW 0211",
        "title": "Art of Empire: The Early Modern Hispanic World (HIAA 0211)",
        "semesters": [
            "Fall"
        ],
        "crn": "18303"
    },
    {
        "code": "EMOW 0522G",
        "title": "An Empire and Republic: The Dutch Golden Age (HIST 0522G)",
        "semesters": [
            "Spring"
        ],
        "crn": "26802"
    },
    {
        "code": "EMOW 0910",
        "title": "On the Dawn of Modernity (POBS 0910)",
        "semesters": [
            "Fall"
        ],
        "crn": "17250"
    },
    {
        "code": "EMOW 1040D",
        "title": "Moli\u00e8re et son monde (FREN 1040D)",
        "semesters": [
            "Fall"
        ],
        "crn": "17796"
    },
    {
        "code": "EMOW 1262",
        "title": "Women, Gender, Feminism in Early Modern Italy (ITAL 1262)",
        "semesters": [
            "Spring"
        ],
        "crn": "27476"
    },
    {
        "code": "EMOW 1266D",
        "title": "British History, 1660-1800 (HIST 1266D)",
        "semesters": [
            "Spring"
        ],
        "crn": "26799"
    },
    {
        "code": "EMOW 1320",
        "title": "Great Authors and Works of Italian Renaissance (ITAL 1320)",
        "semesters": [
            "Fall"
        ],
        "crn": "17789"
    },
    {
        "code": "EMOW 1361L",
        "title": "Milton (ENGL 1361L)",
        "semesters": [
            "Fall"
        ],
        "crn": "17791"
    },
    {
        "code": "EMOW 1410I",
        "title": "Sorcellerie et Renaissance: le sort de la sorci\u00e8re (FREN 1410I)",
        "semesters": [
            "Spring"
        ],
        "crn": "26114"
    },
    {
        "code": "EMOW 1411",
        "title": "Illustrating Indigenous Knowledge (HIAA 1411)",
        "semesters": [
            "Spring"
        ],
        "crn": "27499"
    },
    {
        "code": "EMOW 1430B",
        "title": "Art and Exemplarity in Medieval and Early Modern Literature (COLT 1430B)",
        "semesters": [
            "Fall"
        ],
        "crn": "17799"
    },
    {
        "code": "EMOW 1620",
        "title": "Arts Between Europe and the World 1500-1700 (HIAA 1620)",
        "semesters": [
            "Fall"
        ],
        "crn": "18061"
    },
    {
        "code": "EMOW 1825F",
        "title": "Nature, Knowledge, and Power in Renaissance Europe (HIST 1825F)",
        "semesters": [
            "Spring"
        ],
        "crn": "26801"
    },
    {
        "code": "EMOW 1825H",
        "title": "Science, Medicine and Technology in the 17th Century (HIST 1825H)",
        "semesters": [
            "Fall"
        ],
        "crn": "17252"
    },
    {
        "code": "EMOW 2110K",
        "title": "Vision and Visualization in Literature: The Rhetoric of Enargeia (CLAS 2110K)",
        "semesters": [
            "Fall"
        ],
        "crn": "18057"
    },
    {
        "code": "EMOW 2561V",
        "title": "The Pursuit of Happiness: Transatlantic Literary Culture in the Long Eighteenth Century (ENGL 2561V)",
        "semesters": [
            "Fall"
        ],
        "crn": "17792"
    },
    {
        "code": "EMOW 2970E",
        "title": "Early Modern Continental Europe - Reading (HIST 2970E)",
        "semesters": [
            "Spring"
        ],
        "crn": "26803"
    }
]